pyplatform/database/__init__.py
pyplatform/database/database.py
pyplatform_database-2020.12.1.dist-info/METADATA
pyplatform_database-2020.12.1.dist-info/WHEEL
pyplatform_database-2020.12.1.dist-info/top_level.txt
pyplatform_database-2020.12.1.dist-info/RECORD
