Metadata-Version: 2.1
Name: pyplatform-database
Version: 2020.12.1
Summary: Pyplatform-database package provides read and write functions for Microsoft SQL database.
Home-page: https://github.com/mhadi813/pyplatform
Author: Muhammad Hadi
Author-email: mhadi813@gmail.com
License: BSD
Keywords: google bigquery cloud functions storage jupyterlab python SQL
Platform: UNKNOWN
Classifier: Development Status :: 4 - Beta
Classifier: Intended Audience :: Developers
Classifier: Topic :: Office/Business
Classifier: License :: OSI Approved :: BSD License
Classifier: Programming Language :: Python :: 3.6
Classifier: Programming Language :: Python :: 3.7
Classifier: Programming Language :: Python :: 3.8
Requires-Dist: pyodbc (==4.0.28)
Requires-Dist: sqlalchemy (==1.3.19)
Requires-Dist: xlrd (==1.2.0)
Requires-Dist: XlsxWriter (==1.3.3)
Requires-Dist: openpyxl (==3.0.3)
Requires-Dist: pyplatform-common
